pydaw-1.0.1.dist-info/METADATA
pydaw-1.0.1.dist-info/RECORD
pydaw-1.0.1.dist-info/WHEEL
pydaw-1.0.1.dist-info/entry_points.txt
pydaw-1.0.1.dist-info/top_level.txt
pythoncli/__init__.py
pythoncli/__main__.py
pythoncli/classmodule.py
pythoncli/effectsmodule.py
pythoncli/funcmodule.py
pythoncli/generatingmodule.py
pythoncli/loadingmodule.py
pythoncli/resamplemodule.py
pythoncli/supereffectmodule.py
