Metadata-Version: 2.1
Name: pydaw
Version: 1.0.1
Summary: A Python CLI
Home-page: https://gitlab.com/peterHassaballah/pythoncli
Author: Peter Hassaballah
Author-email: peter.hassaballah@gmail.com
License: UNKNOWN
Platform: UNKNOWN
Requires-Dist: fire (==0.1.3)
Requires-Dist: pydub (==0.23.1)
